{
"type": "FeatureCollection",
"name": "Kerkebuurt-39_Marken_names",
"crs": { "type": "name", "properties": { "name": "urn:ogc:def:crs:OGC:1.3:CRS84" } },
"features": [
{ "type": "Feature", "properties": { "lat": 52.460492570146094, "lng": 5.1060277212115839, "Gebied": "Kerkebuurt-39" }, "geometry": { "type": "Point", "coordinates": [ 5.106027031616332, 52.460492493730733 ] } }
]
}
